binara/__init__.py
binara/binara_ext.pyi
binara/binara_ext.cpython-39-darwin.so
binara/internal/__init__.py
binara/internal/data_preparation.py
binara/.dylibs/libomp.dylib
binara-0.0.1.dist-info/RECORD
binara-0.0.1.dist-info/WHEEL
binara-0.0.1.dist-info/METADATA
binara-0.0.1.dist-info/licenses/LICENSE.txt
