Metadata-Version: 2.1
Name: binara
Version: 0.0.1
Project-URL: Homepage, https://github.com/golmschenk/binara
Requires-Python: >=3.9
